Adafruit_LED_Backpack/Matrix8x8.py
Adafruit_LED_Backpack/BicolorBargraph24.py
Adafruit_LED_Backpack/HT16K33.py
Adafruit_LED_Backpack/AlphaNum4.py
Adafruit_LED_Backpack/__init__.py
Adafruit_LED_Backpack/BicolorMatrix8x8.py
Adafruit_LED_Backpack/SevenSegment.py
Adafruit_LED_Backpack-1.8.1.dist-info/metadata.json
Adafruit_LED_Backpack-1.8.1.dist-info/METADATA
Adafruit_LED_Backpack-1.8.1.dist-info/RECORD
Adafruit_LED_Backpack-1.8.1.dist-info/WHEEL
Adafruit_LED_Backpack-1.8.1.dist-info/DESCRIPTION.rst
Adafruit_LED_Backpack-1.8.1.dist-info/dependency_links.txt
Adafruit_LED_Backpack-1.8.1.dist-info/top_level.txt
