Metadata-Version: 2.0
Name: Adafruit-LED-Backpack
Version: 1.8.1
Summary: Library to control LED backpack displays such as 8x8 single and bi-color matrices, bargraphs, 7 segment, and 14 segment displays.
Home-page: https://github.com/adafruit/Adafruit_Python_LED_Backpack/
Author: Tony DiCola
Author-email: tdicola@adafruit.com
License: MIT
Platform: UNKNOWN
Classifier: Development Status :: 4 - Beta
Classifier: Operating System :: POSIX :: Linux
Classifier: License :: OSI Approved :: MIT License
Classifier: Intended Audience :: Developers
Classifier: Programming Language :: Python :: 2.7
Classifier: Programming Language :: Python :: 3
Classifier: Topic :: Software Development
Classifier: Topic :: System :: Hardware
Requires-Dist: Adafruit-GPIO (>=0.6.5)
